{
  "timestamp": "20260629_073059",
  "action": "URL_UPDATED",
  "total": 200,
  "success": 200,
  "errors": 0,
  "processed": 200,
  "results": [
    {
      "url": "https://systems-analysis.ru/int/BBQ_(Bias_Benchmark_for_Question_Answering)_(EL)",
      "status": "success",
      "notifyTime": ""
    },
    {
      "url": "https://systems-analysis.ru/int/BBQ_(Bias_Benchmark_for_Question_Answering)_(ES)",
      "status": "success",
      "notifyTime": ""
    },
    {
      "url": "https://systems-analysis.ru/int/BBQ_(Bias_Benchmark_for_Question_Answering)_(FA)",
      "status": "success",
      "notifyTime": ""
    },
    {
      "url": "https://systems-analysis.ru/int/BBQ_(Bias_Benchmark_for_Question_Answering)_(FR)",
      "status": "success",
      "notifyTime": ""
    },
    {
      "url": "https://systems-analysis.ru/int/BBQ_(Bias_Benchmark_for_Question_Answering)_(HE)",
      "status": "success",
      "notifyTime": ""
    },
    {
      "url": "https://systems-analysis.ru/int/BBQ_(Bias_Benchmark_for_Question_Answering)_(HI)",
      "status": "success",
      "notifyTime": ""
    },
    {
      "url": "https://systems-analysis.ru/int/BBQ_(Bias_Benchmark_for_Question_Answering)_(HU)",
      "status": "success",
      "notifyTime": ""
    },
    {
      "url": "https://systems-analysis.ru/int/BBQ_(Bias_Benchmark_for_Question_Answering)_(ID)",
      "status": "success",
      "notifyTime": ""
    },
    {
      "url": "https://systems-analysis.ru/int/BBQ_(Bias_Benchmark_for_Question_Answering)_(IT)",
      "status": "success",
      "notifyTime": ""
    },
    {
      "url": "https://systems-analysis.ru/int/BBQ_(Bias_Benchmark_for_Question_Answering)_(KO)",
      "status": "success",
      "notifyTime": ""
    },
    {
      "url": "https://systems-analysis.ru/int/BBQ_(Bias_Benchmark_for_Question_Answering)_(NL)",
      "status": "success",
      "notifyTime": ""
    },
    {
      "url": "https://systems-analysis.ru/int/BBQ_(Bias_Benchmark_for_Question_Answering)_(PL)",
      "status": "success",
      "notifyTime": ""
    },
    {
      "url": "https://systems-analysis.ru/int/BBQ_(Bias_Benchmark_for_Question_Answering)_(PT)",
      "status": "success",
      "notifyTime": ""
    },
    {
      "url": "https://systems-analysis.ru/int/BBQ_(Bias_Benchmark_for_Question_Answering)_(RO)",
      "status": "success",
      "notifyTime": ""
    },
    {
      "url": "https://systems-analysis.ru/int/BBQ_(Bias_Benchmark_for_Question_Answering)_(SV)",
      "status": "success",
      "notifyTime": ""
    },
    {
      "url": "https://systems-analysis.ru/int/BBQ_(Bias_Benchmark_for_Question_Answering)_(TH)",
      "status": "success",
      "notifyTime": ""
    },
    {
      "url": "https://systems-analysis.ru/int/BBQ_(Bias_Benchmark_for_Question_Answering)_(TL)",
      "status": "success",
      "notifyTime": ""
    },
    {
      "url": "https://systems-analysis.ru/int/BBQ_(Bias_Benchmark_for_Question_Answering)_(TR)",
      "status": "success",
      "notifyTime": ""
    },
    {
      "url": "https://systems-analysis.ru/int/BBQ_(Bias_Benchmark_for_Question_Answering)_(UR)",
      "status": "success",
      "notifyTime": ""
    },
    {
      "url": "https://systems-analysis.ru/int/BBQ_(Bias_Benchmark_for_Question_Answering)_(VI)",
      "status": "success",
      "notifyTime": ""
    },
    {
      "url": "https://systems-analysis.ru/int/BBQ_(Bias_Benchmark_for_Question_Answering)_—_معيار_التحيز_للإجابة_على_الأسئلة",
      "status": "success",
      "notifyTime": ""
    },
    {
      "url": "https://systems-analysis.ru/int/BBQ_(Bias_Benchmark_for_Question_Answering)_—_質問応答バイアスベンチマーク",
      "status": "success",
      "notifyTime": ""
    },
    {
      "url": "https://systems-analysis.ru/int/BBQ_(Bias_Benchmark_for_Question_Answering)_—_问答偏见基准",
      "status": "success",
      "notifyTime": ""
    },
    {
      "url": "https://systems-analysis.ru/int/BERTScore_(metric)_(BG)",
      "status": "success",
      "notifyTime": ""
    },
    {
      "url": "https://systems-analysis.ru/int/BERTScore_(metric)_(BN)",
      "status": "success",
      "notifyTime": ""
    },
    {
      "url": "https://systems-analysis.ru/int/BERTScore_(metric)_(CS)",
      "status": "success",
      "notifyTime": ""
    },
    {
      "url": "https://systems-analysis.ru/int/BERTScore_(metric)_(DE)",
      "status": "success",
      "notifyTime": ""
    },
    {
      "url": "https://systems-analysis.ru/int/BERTScore_(metric)_(EL)",
      "status": "success",
      "notifyTime": ""
    },
    {
      "url": "https://systems-analysis.ru/int/BERTScore_(metric)_(ES)",
      "status": "success",
      "notifyTime": ""
    },
    {
      "url": "https://systems-analysis.ru/int/BERTScore_(metric)_(FA)",
      "status": "success",
      "notifyTime": ""
    },
    {
      "url": "https://systems-analysis.ru/int/BERTScore_(metric)_(FR)",
      "status": "success",
      "notifyTime": ""
    },
    {
      "url": "https://systems-analysis.ru/int/BERTScore_(metric)_(HE)",
      "status": "success",
      "notifyTime": ""
    },
    {
      "url": "https://systems-analysis.ru/int/BERTScore_(metric)_(HI)",
      "status": "success",
      "notifyTime": ""
    },
    {
      "url": "https://systems-analysis.ru/int/BERTScore_(metric)_(HU)",
      "status": "success",
      "notifyTime": ""
    },
    {
      "url": "https://systems-analysis.ru/int/BERTScore_(metric)_(ID)",
      "status": "success",
      "notifyTime": ""
    },
    {
      "url": "https://systems-analysis.ru/int/BERTScore_(metric)_(IT)",
      "status": "success",
      "notifyTime": ""
    },
    {
      "url": "https://systems-analysis.ru/int/BERTScore_(metric)_(KO)",
      "status": "success",
      "notifyTime": ""
    },
    {
      "url": "https://systems-analysis.ru/int/BERTScore_(metric)_(NL)",
      "status": "success",
      "notifyTime": ""
    },
    {
      "url": "https://systems-analysis.ru/int/BERTScore_(metric)_(PL)",
      "status": "success",
      "notifyTime": ""
    },
    {
      "url": "https://systems-analysis.ru/int/BERTScore_(metric)_(PT)",
      "status": "success",
      "notifyTime": ""
    },
    {
      "url": "https://systems-analysis.ru/int/BERTScore_(metric)_(RO)",
      "status": "success",
      "notifyTime": ""
    },
    {
      "url": "https://systems-analysis.ru/int/BERTScore_(metric)_(SV)",
      "status": "success",
      "notifyTime": ""
    },
    {
      "url": "https://systems-analysis.ru/int/BERTScore_(metric)_(TH)",
      "status": "success",
      "notifyTime": ""
    },
    {
      "url": "https://systems-analysis.ru/int/BERTScore_(metric)_(TL)",
      "status": "success",
      "notifyTime": ""
    },
    {
      "url": "https://systems-analysis.ru/int/BERTScore_(metric)_(TR)",
      "status": "success",
      "notifyTime": ""
    },
    {
      "url": "https://systems-analysis.ru/int/BERTScore_(metric)_(UR)",
      "status": "success",
      "notifyTime": ""
    },
    {
      "url": "https://systems-analysis.ru/int/BERTScore_(metric)_(VI)",
      "status": "success",
      "notifyTime": ""
    },
    {
      "url": "https://systems-analysis.ru/int/BERTScore_(metric)_—_BERTスコア",
      "status": "success",
      "notifyTime": ""
    },
    {
      "url": "https://systems-analysis.ru/int/BERTScore_(metric)_—_BERT评分",
      "status": "success",
      "notifyTime": ""
    },
    {
      "url": "https://systems-analysis.ru/int/BERTScore_(metric)_—_مقياس_بيرت_سكور",
      "status": "success",
      "notifyTime": ""
    },
    {
      "url": "https://systems-analysis.ru/int/BERT_(Sprachmodell)",
      "status": "success",
      "notifyTime": ""
    },
    {
      "url": "https://systems-analysis.ru/int/BERT_(language_model)_(BG)",
      "status": "success",
      "notifyTime": ""
    },
    {
      "url": "https://systems-analysis.ru/int/BERT_(language_model)_(BN)",
      "status": "success",
      "notifyTime": ""
    },
    {
      "url": "https://systems-analysis.ru/int/BERT_(language_model)_(CS)",
      "status": "success",
      "notifyTime": ""
    },
    {
      "url": "https://systems-analysis.ru/int/BERT_(language_model)_(EL)",
      "status": "success",
      "notifyTime": ""
    },
    {
      "url": "https://systems-analysis.ru/int/BERT_(language_model)_(FA)",
      "status": "success",
      "notifyTime": ""
    },
    {
      "url": "https://systems-analysis.ru/int/BERT_(language_model)_(HE)",
      "status": "success",
      "notifyTime": ""
    },
    {
      "url": "https://systems-analysis.ru/int/BERT_(language_model)_(HI)",
      "status": "success",
      "notifyTime": ""
    },
    {
      "url": "https://systems-analysis.ru/int/BERT_(language_model)_(HU)",
      "status": "success",
      "notifyTime": ""
    },
    {
      "url": "https://systems-analysis.ru/int/BERT_(language_model)_(ID)",
      "status": "success",
      "notifyTime": ""
    },
    {
      "url": "https://systems-analysis.ru/int/BERT_(language_model)_(IT)",
      "status": "success",
      "notifyTime": ""
    },
    {
      "url": "https://systems-analysis.ru/int/BERT_(language_model)_(KO)",
      "status": "success",
      "notifyTime": ""
    },
    {
      "url": "https://systems-analysis.ru/int/BERT_(language_model)_(NL)",
      "status": "success",
      "notifyTime": ""
    },
    {
      "url": "https://systems-analysis.ru/int/BERT_(language_model)_(PL)",
      "status": "success",
      "notifyTime": ""
    },
    {
      "url": "https://systems-analysis.ru/int/BERT_(language_model)_(RO)",
      "status": "success",
      "notifyTime": ""
    },
    {
      "url": "https://systems-analysis.ru/int/BERT_(language_model)_(SV)",
      "status": "success",
      "notifyTime": ""
    },
    {
      "url": "https://systems-analysis.ru/int/BERT_(language_model)_(TH)",
      "status": "success",
      "notifyTime": ""
    },
    {
      "url": "https://systems-analysis.ru/int/BERT_(language_model)_(TL)",
      "status": "success",
      "notifyTime": ""
    },
    {
      "url": "https://systems-analysis.ru/int/BERT_(language_model)_(TR)",
      "status": "success",
      "notifyTime": ""
    },
    {
      "url": "https://systems-analysis.ru/int/BERT_(language_model)_(UR)",
      "status": "success",
      "notifyTime": ""
    },
    {
      "url": "https://systems-analysis.ru/int/BERT_(language_model)_(VI)",
      "status": "success",
      "notifyTime": ""
    },
    {
      "url": "https://systems-analysis.ru/int/BERT_(language_model)_—_بيرت",
      "status": "success",
      "notifyTime": ""
    },
    {
      "url": "https://systems-analysis.ru/int/BERT_(language_model)_—_バート",
      "status": "success",
      "notifyTime": ""
    },
    {
      "url": "https://systems-analysis.ru/int/BERT_(language_model)_—_来自变换器的双向编码器表示",
      "status": "success",
      "notifyTime": ""
    },
    {
      "url": "https://systems-analysis.ru/int/BERT_(modelo_de_lenguaje)",
      "status": "success",
      "notifyTime": ""
    },
    {
      "url": "https://systems-analysis.ru/int/BERT_(modelo_de_linguagem)",
      "status": "success",
      "notifyTime": ""
    },
    {
      "url": "https://systems-analysis.ru/int/BERT_(modèle_de_langage)",
      "status": "success",
      "notifyTime": ""
    },
    {
      "url": "https://systems-analysis.ru/int/BIG-bench_(benchmark)_(BG)",
      "status": "success",
      "notifyTime": ""
    },
    {
      "url": "https://systems-analysis.ru/int/BIG-bench_(benchmark)_(BN)",
      "status": "success",
      "notifyTime": ""
    },
    {
      "url": "https://systems-analysis.ru/int/BIG-bench_(benchmark)_(CS)",
      "status": "success",
      "notifyTime": ""
    },
    {
      "url": "https://systems-analysis.ru/int/BIG-bench_(benchmark)_(DE)",
      "status": "success",
      "notifyTime": ""
    },
    {
      "url": "https://systems-analysis.ru/int/BIG-bench_(benchmark)_(EL)",
      "status": "success",
      "notifyTime": ""
    },
    {
      "url": "https://systems-analysis.ru/int/BIG-bench_(benchmark)_(ES)",
      "status": "success",
      "notifyTime": ""
    },
    {
      "url": "https://systems-analysis.ru/int/BIG-bench_(benchmark)_(FA)",
      "status": "success",
      "notifyTime": ""
    },
    {
      "url": "https://systems-analysis.ru/int/BIG-bench_(benchmark)_(FR)",
      "status": "success",
      "notifyTime": ""
    },
    {
      "url": "https://systems-analysis.ru/int/BIG-bench_(benchmark)_(HE)",
      "status": "success",
      "notifyTime": ""
    },
    {
      "url": "https://systems-analysis.ru/int/BIG-bench_(benchmark)_(HI)",
      "status": "success",
      "notifyTime": ""
    },
    {
      "url": "https://systems-analysis.ru/int/BIG-bench_(benchmark)_(HU)",
      "status": "success",
      "notifyTime": ""
    },
    {
      "url": "https://systems-analysis.ru/int/BIG-bench_(benchmark)_(ID)",
      "status": "success",
      "notifyTime": ""
    },
    {
      "url": "https://systems-analysis.ru/int/BIG-bench_(benchmark)_(IT)",
      "status": "success",
      "notifyTime": ""
    },
    {
      "url": "https://systems-analysis.ru/int/BIG-bench_(benchmark)_(KO)",
      "status": "success",
      "notifyTime": ""
    },
    {
      "url": "https://systems-analysis.ru/int/BIG-bench_(benchmark)_(NL)",
      "status": "success",
      "notifyTime": ""
    },
    {
      "url": "https://systems-analysis.ru/int/BIG-bench_(benchmark)_(PL)",
      "status": "success",
      "notifyTime": ""
    },
    {
      "url": "https://systems-analysis.ru/int/BIG-bench_(benchmark)_(PT)",
      "status": "success",
      "notifyTime": ""
    },
    {
      "url": "https://systems-analysis.ru/int/BIG-bench_(benchmark)_(RO)",
      "status": "success",
      "notifyTime": ""
    },
    {
      "url": "https://systems-analysis.ru/int/BIG-bench_(benchmark)_(SV)",
      "status": "success",
      "notifyTime": ""
    },
    {
      "url": "https://systems-analysis.ru/int/BIG-bench_(benchmark)_(TH)",
      "status": "success",
      "notifyTime": ""
    },
    {
      "url": "https://systems-analysis.ru/int/BIG-bench_(benchmark)_(TL)",
      "status": "success",
      "notifyTime": ""
    },
    {
      "url": "https://systems-analysis.ru/int/BIG-bench_(benchmark)_(TR)",
      "status": "success",
      "notifyTime": ""
    },
    {
      "url": "https://systems-analysis.ru/int/BIG-bench_(benchmark)_(UR)",
      "status": "success",
      "notifyTime": ""
    },
    {
      "url": "https://systems-analysis.ru/int/BIG-bench_(benchmark)_(VI)",
      "status": "success",
      "notifyTime": ""
    },
    {
      "url": "https://systems-analysis.ru/int/BIG-bench_(benchmark)_—_معيار_بيغ-بنش",
      "status": "success",
      "notifyTime": ""
    },
    {
      "url": "https://systems-analysis.ru/int/BIG-bench_(benchmark)_—_ビッグベンチ",
      "status": "success",
      "notifyTime": ""
    },
    {
      "url": "https://systems-analysis.ru/int/BIG-bench_(benchmark)_—_大规模基准测试",
      "status": "success",
      "notifyTime": ""
    },
    {
      "url": "https://systems-analysis.ru/int/BLEU_(Bilingual_Evaluation_Understudy)_(BG)",
      "status": "success",
      "notifyTime": ""
    },
    {
      "url": "https://systems-analysis.ru/int/BLEU_(Bilingual_Evaluation_Understudy)_(BN)",
      "status": "success",
      "notifyTime": ""
    },
    {
      "url": "https://systems-analysis.ru/int/BLEU_(Bilingual_Evaluation_Understudy)_(CS)",
      "status": "success",
      "notifyTime": ""
    },
    {
      "url": "https://systems-analysis.ru/int/BLEU_(Bilingual_Evaluation_Understudy)_(DE)",
      "status": "success",
      "notifyTime": ""
    },
    {
      "url": "https://systems-analysis.ru/int/BLEU_(Bilingual_Evaluation_Understudy)_(EL)",
      "status": "success",
      "notifyTime": ""
    },
    {
      "url": "https://systems-analysis.ru/int/BLEU_(Bilingual_Evaluation_Understudy)_(ES)",
      "status": "success",
      "notifyTime": ""
    },
    {
      "url": "https://systems-analysis.ru/int/BLEU_(Bilingual_Evaluation_Understudy)_(FA)",
      "status": "success",
      "notifyTime": ""
    },
    {
      "url": "https://systems-analysis.ru/int/BLEU_(Bilingual_Evaluation_Understudy)_(FR)",
      "status": "success",
      "notifyTime": ""
    },
    {
      "url": "https://systems-analysis.ru/int/BLEU_(Bilingual_Evaluation_Understudy)_(HE)",
      "status": "success",
      "notifyTime": ""
    },
    {
      "url": "https://systems-analysis.ru/int/BLEU_(Bilingual_Evaluation_Understudy)_(HI)",
      "status": "success",
      "notifyTime": ""
    },
    {
      "url": "https://systems-analysis.ru/int/BLEU_(Bilingual_Evaluation_Understudy)_(HU)",
      "status": "success",
      "notifyTime": ""
    },
    {
      "url": "https://systems-analysis.ru/int/BLEU_(Bilingual_Evaluation_Understudy)_(ID)",
      "status": "success",
      "notifyTime": ""
    },
    {
      "url": "https://systems-analysis.ru/int/BLEU_(Bilingual_Evaluation_Understudy)_(IT)",
      "status": "success",
      "notifyTime": ""
    },
    {
      "url": "https://systems-analysis.ru/int/BLEU_(Bilingual_Evaluation_Understudy)_(KO)",
      "status": "success",
      "notifyTime": ""
    },
    {
      "url": "https://systems-analysis.ru/int/BLEU_(Bilingual_Evaluation_Understudy)_(NL)",
      "status": "success",
      "notifyTime": ""
    },
    {
      "url": "https://systems-analysis.ru/int/BLEU_(Bilingual_Evaluation_Understudy)_(PL)",
      "status": "success",
      "notifyTime": ""
    },
    {
      "url": "https://systems-analysis.ru/int/BLEU_(Bilingual_Evaluation_Understudy)_(PT)",
      "status": "success",
      "notifyTime": ""
    },
    {
      "url": "https://systems-analysis.ru/int/BLEU_(Bilingual_Evaluation_Understudy)_(RO)",
      "status": "success",
      "notifyTime": ""
    },
    {
      "url": "https://systems-analysis.ru/int/BLEU_(Bilingual_Evaluation_Understudy)_(SV)",
      "status": "success",
      "notifyTime": ""
    },
    {
      "url": "https://systems-analysis.ru/int/BLEU_(Bilingual_Evaluation_Understudy)_(TH)",
      "status": "success",
      "notifyTime": ""
    },
    {
      "url": "https://systems-analysis.ru/int/BLEU_(Bilingual_Evaluation_Understudy)_(TL)",
      "status": "success",
      "notifyTime": ""
    },
    {
      "url": "https://systems-analysis.ru/int/BLEU_(Bilingual_Evaluation_Understudy)_(TR)",
      "status": "success",
      "notifyTime": ""
    },
    {
      "url": "https://systems-analysis.ru/int/BLEU_(Bilingual_Evaluation_Understudy)_(UR)",
      "status": "success",
      "notifyTime": ""
    },
    {
      "url": "https://systems-analysis.ru/int/BLEU_(Bilingual_Evaluation_Understudy)_(VI)",
      "status": "success",
      "notifyTime": ""
    },
    {
      "url": "https://systems-analysis.ru/int/BLEU_(Bilingual_Evaluation_Understudy)_—_مقياس_بلو",
      "status": "success",
      "notifyTime": ""
    },
    {
      "url": "https://systems-analysis.ru/int/BLEU_(Bilingual_Evaluation_Understudy)_—_ブルー",
      "status": "success",
      "notifyTime": ""
    },
    {
      "url": "https://systems-analysis.ru/int/BLEU_(Bilingual_Evaluation_Understudy)_—_双语评估替补",
      "status": "success",
      "notifyTime": ""
    },
    {
      "url": "https://systems-analysis.ru/int/BLOOM_(Sprachmodell)",
      "status": "success",
      "notifyTime": ""
    },
    {
      "url": "https://systems-analysis.ru/int/BLOOM_(language_model)_(BG)",
      "status": "success",
      "notifyTime": ""
    },
    {
      "url": "https://systems-analysis.ru/int/BLOOM_(language_model)_(BN)",
      "status": "success",
      "notifyTime": ""
    },
    {
      "url": "https://systems-analysis.ru/int/BLOOM_(language_model)_(CS)",
      "status": "success",
      "notifyTime": ""
    },
    {
      "url": "https://systems-analysis.ru/int/BLOOM_(language_model)_(EL)",
      "status": "success",
      "notifyTime": ""
    },
    {
      "url": "https://systems-analysis.ru/int/BLOOM_(language_model)_(FA)",
      "status": "success",
      "notifyTime": ""
    },
    {
      "url": "https://systems-analysis.ru/int/BLOOM_(language_model)_(HE)",
      "status": "success",
      "notifyTime": ""
    },
    {
      "url": "https://systems-analysis.ru/int/BLOOM_(language_model)_(HI)",
      "status": "success",
      "notifyTime": ""
    },
    {
      "url": "https://systems-analysis.ru/int/BLOOM_(language_model)_(HU)",
      "status": "success",
      "notifyTime": ""
    },
    {
      "url": "https://systems-analysis.ru/int/BLOOM_(language_model)_(ID)",
      "status": "success",
      "notifyTime": ""
    },
    {
      "url": "https://systems-analysis.ru/int/BLOOM_(language_model)_(IT)",
      "status": "success",
      "notifyTime": ""
    },
    {
      "url": "https://systems-analysis.ru/int/BLOOM_(language_model)_(KO)",
      "status": "success",
      "notifyTime": ""
    },
    {
      "url": "https://systems-analysis.ru/int/BLOOM_(language_model)_(NL)",
      "status": "success",
      "notifyTime": ""
    },
    {
      "url": "https://systems-analysis.ru/int/BLOOM_(language_model)_(PL)",
      "status": "success",
      "notifyTime": ""
    },
    {
      "url": "https://systems-analysis.ru/int/BLOOM_(language_model)_(RO)",
      "status": "success",
      "notifyTime": ""
    },
    {
      "url": "https://systems-analysis.ru/int/BLOOM_(language_model)_(SV)",
      "status": "success",
      "notifyTime": ""
    },
    {
      "url": "https://systems-analysis.ru/int/BLOOM_(language_model)_(TH)",
      "status": "success",
      "notifyTime": ""
    },
    {
      "url": "https://systems-analysis.ru/int/BLOOM_(language_model)_(TL)",
      "status": "success",
      "notifyTime": ""
    },
    {
      "url": "https://systems-analysis.ru/int/BLOOM_(language_model)_(TR)",
      "status": "success",
      "notifyTime": ""
    },
    {
      "url": "https://systems-analysis.ru/int/BLOOM_(language_model)_(UR)",
      "status": "success",
      "notifyTime": ""
    },
    {
      "url": "https://systems-analysis.ru/int/BLOOM_(language_model)_(VI)",
      "status": "success",
      "notifyTime": ""
    },
    {
      "url": "https://systems-analysis.ru/int/BLOOM_(language_model)_—_بلوم",
      "status": "success",
      "notifyTime": ""
    },
    {
      "url": "https://systems-analysis.ru/int/BLOOM_(language_model)_—_ブルーム",
      "status": "success",
      "notifyTime": ""
    },
    {
      "url": "https://systems-analysis.ru/int/BLOOM_(language_model)_—_大型开放多语言语言模型",
      "status": "success",
      "notifyTime": ""
    },
    {
      "url": "https://systems-analysis.ru/int/BLOOM_(modelo_de_lenguaje)",
      "status": "success",
      "notifyTime": ""
    },
    {
      "url": "https://systems-analysis.ru/int/BLOOM_(modelo_de_linguagem)",
      "status": "success",
      "notifyTime": ""
    },
    {
      "url": "https://systems-analysis.ru/int/BLOOM_(modèle_de_langage)",
      "status": "success",
      "notifyTime": ""
    },
    {
      "url": "https://systems-analysis.ru/int/BOLD_(Bias_in_Open-Ended_Language_Generation_Dataset)_(BG)",
      "status": "success",
      "notifyTime": ""
    },
    {
      "url": "https://systems-analysis.ru/int/BOLD_(Bias_in_Open-Ended_Language_Generation_Dataset)_(BN)",
      "status": "success",
      "notifyTime": ""
    },
    {
      "url": "https://systems-analysis.ru/int/BOLD_(Bias_in_Open-Ended_Language_Generation_Dataset)_(CS)",
      "status": "success",
      "notifyTime": ""
    },
    {
      "url": "https://systems-analysis.ru/int/BOLD_(Bias_in_Open-Ended_Language_Generation_Dataset)_(DE)",
      "status": "success",
      "notifyTime": ""
    },
    {
      "url": "https://systems-analysis.ru/int/BOLD_(Bias_in_Open-Ended_Language_Generation_Dataset)_(EL)",
      "status": "success",
      "notifyTime": ""
    },
    {
      "url": "https://systems-analysis.ru/int/BOLD_(Bias_in_Open-Ended_Language_Generation_Dataset)_(ES)",
      "status": "success",
      "notifyTime": ""
    },
    {
      "url": "https://systems-analysis.ru/int/BOLD_(Bias_in_Open-Ended_Language_Generation_Dataset)_(FA)",
      "status": "success",
      "notifyTime": ""
    },
    {
      "url": "https://systems-analysis.ru/int/BOLD_(Bias_in_Open-Ended_Language_Generation_Dataset)_(FR)",
      "status": "success",
      "notifyTime": ""
    },
    {
      "url": "https://systems-analysis.ru/int/BOLD_(Bias_in_Open-Ended_Language_Generation_Dataset)_(HE)",
      "status": "success",
      "notifyTime": ""
    },
    {
      "url": "https://systems-analysis.ru/int/BOLD_(Bias_in_Open-Ended_Language_Generation_Dataset)_(HI)",
      "status": "success",
      "notifyTime": ""
    },
    {
      "url": "https://systems-analysis.ru/int/BOLD_(Bias_in_Open-Ended_Language_Generation_Dataset)_(HU)",
      "status": "success",
      "notifyTime": ""
    },
    {
      "url": "https://systems-analysis.ru/int/BOLD_(Bias_in_Open-Ended_Language_Generation_Dataset)_(ID)",
      "status": "success",
      "notifyTime": ""
    },
    {
      "url": "https://systems-analysis.ru/int/BOLD_(Bias_in_Open-Ended_Language_Generation_Dataset)_(IT)",
      "status": "success",
      "notifyTime": ""
    },
    {
      "url": "https://systems-analysis.ru/int/BOLD_(Bias_in_Open-Ended_Language_Generation_Dataset)_(KO)",
      "status": "success",
      "notifyTime": ""
    },
    {
      "url": "https://systems-analysis.ru/int/BOLD_(Bias_in_Open-Ended_Language_Generation_Dataset)_(NL)",
      "status": "success",
      "notifyTime": ""
    },
    {
      "url": "https://systems-analysis.ru/int/BOLD_(Bias_in_Open-Ended_Language_Generation_Dataset)_(PL)",
      "status": "success",
      "notifyTime": ""
    },
    {
      "url": "https://systems-analysis.ru/int/BOLD_(Bias_in_Open-Ended_Language_Generation_Dataset)_(PT)",
      "status": "success",
      "notifyTime": ""
    },
    {
      "url": "https://systems-analysis.ru/int/BOLD_(Bias_in_Open-Ended_Language_Generation_Dataset)_(RO)",
      "status": "success",
      "notifyTime": ""
    },
    {
      "url": "https://systems-analysis.ru/int/BOLD_(Bias_in_Open-Ended_Language_Generation_Dataset)_(SV)",
      "status": "success",
      "notifyTime": ""
    },
    {
      "url": "https://systems-analysis.ru/int/BOLD_(Bias_in_Open-Ended_Language_Generation_Dataset)_(TH)",
      "status": "success",
      "notifyTime": ""
    },
    {
      "url": "https://systems-analysis.ru/int/BOLD_(Bias_in_Open-Ended_Language_Generation_Dataset)_(TL)",
      "status": "success",
      "notifyTime": ""
    },
    {
      "url": "https://systems-analysis.ru/int/BOLD_(Bias_in_Open-Ended_Language_Generation_Dataset)_(TR)",
      "status": "success",
      "notifyTime": ""
    },
    {
      "url": "https://systems-analysis.ru/int/BOLD_(Bias_in_Open-Ended_Language_Generation_Dataset)_(UR)",
      "status": "success",
      "notifyTime": ""
    },
    {
      "url": "https://systems-analysis.ru/int/BOLD_(Bias_in_Open-Ended_Language_Generation_Dataset)_(VI)",
      "status": "success",
      "notifyTime": ""
    },
    {
      "url": "https://systems-analysis.ru/int/BOLD_(Bias_in_Open-Ended_Language_Generation_Dataset)_—_BOLD",
      "status": "success",
      "notifyTime": ""
    },
    {
      "url": "https://systems-analysis.ru/int/BOLD_(Bias_in_Open-Ended_Language_Generation_Dataset)_—_オープンエンド言語生成におけるバイアスデータセット",
      "status": "success",
      "notifyTime": ""
    },
    {
      "url": "https://systems-analysis.ru/int/BOLD_(Bias_in_Open-Ended_Language_Generation_Dataset)_—_开放式语言生成偏见数据集",
      "status": "success",
      "notifyTime": ""
    },
    {
      "url": "https://systems-analysis.ru/int/BT'de_Sistem_Analizi",
      "status": "success",
      "notifyTime": ""
    },
    {
      "url": "https://systems-analysis.ru/int/Badania_operacyjne",
      "status": "success",
      "notifyTime": ""
    },
    {
      "url": "https://systems-analysis.ru/int/Badania_systemowe._Rocznik",
      "status": "success",
      "notifyTime": ""
    },
    {
      "url": "https://systems-analysis.ru/int/Badania_systemowe._Wydanie_1969",
      "status": "success",
      "notifyTime": ""
    },
    {
      "url": "https://systems-analysis.ru/int/Badania_systemowe._Wydanie_1970",
      "status": "success",
      "notifyTime": ""
    },
    {
      "url": "https://systems-analysis.ru/int/Badania_systemowe._Wydanie_1971",
      "status": "success",
      "notifyTime": ""
    },
    {
      "url": "https://systems-analysis.ru/int/Badania_systemowe._Wydanie_1972",
      "status": "success",
      "notifyTime": ""
    },
    {
      "url": "https://systems-analysis.ru/int/Badania_systemowe._Wydanie_1973",
      "status": "success",
      "notifyTime": ""
    },
    {
      "url": "https://systems-analysis.ru/int/Badania_systemowe._Wydanie_1974",
      "status": "success",
      "notifyTime": ""
    },
    {
      "url": "https://systems-analysis.ru/int/Badania_systemowe._Wydanie_1975",
      "status": "success",
      "notifyTime": ""
    },
    {
      "url": "https://systems-analysis.ru/int/Badania_systemowe._Wydanie_1976",
      "status": "success",
      "notifyTime": ""
    },
    {
      "url": "https://systems-analysis.ru/int/Badania_systemowe._Wydanie_1977",
      "status": "success",
      "notifyTime": ""
    },
    {
      "url": "https://systems-analysis.ru/int/Badania_systemowe._Wydanie_1978",
      "status": "success",
      "notifyTime": ""
    },
    {
      "url": "https://systems-analysis.ru/int/Badania_systemowe._Wydanie_1979",
      "status": "success",
      "notifyTime": ""
    },
    {
      "url": "https://systems-analysis.ru/int/Badania_systemowe._Wydanie_1980",
      "status": "success",
      "notifyTime": ""
    }
  ]
}